Metadata-Version: 2.1
Name: muz
Version: 0.0.4
Summary: A console music player.
Home-page: https://github.com/userElaina
Author: userElaina
Author-email: userElaina@google.com
License: UNKNOWN
Project-URL: Source, https://github.com/userElaina/console-music-player
Keywords: userelaina
Platform: UNKNOWN
Classifier: License :: OSI Approved :: MIT License
Classifier: Programming Language :: Python :: 3
Classifier: Programming Language :: Python :: 3.6
Classifier: Programming Language :: Python :: 3.7
Classifier: Programming Language :: Python :: 3.8
Classifier: Programming Language :: Python :: 3.9
Requires-Python: >=3.6
License-File: LICENSE
Requires-Dist: userelaina (==0.0.4)
